rsudp/__init__.py
rsudp/_version.py
rsudp/c_alert.py
rsudp/c_alertsound.py
rsudp/c_consumer.py
rsudp/c_custom.py
rsudp/c_forward.py
rsudp/c_plot_controller.py
rsudp/c_plots.py
rsudp/c_printraw.py
rsudp/c_rsam.py
rsudp/c_settings.py
rsudp/c_telegram.py
rsudp/c_testing.py
rsudp/c_tweet.py
rsudp/c_write.py
rsudp/client.py
rsudp/entry_points.py
rsudp/helpers.py
rsudp/p_producer.py
rsudp/packetize.py
rsudp/packetloss.py
rsudp/raspberryshake.py
rsudp/t_testdata.py
rsudp/test.py
rsudp/img/__init__.py
rsudp/img/icon.ico
rsudp/img/icon.png
rsudp/img/version1-01-small.png
rsudp/rs_sounds/__init__.py
rsudp/rs_sounds/alarm.mp3
rsudp/rs_sounds/beeps.mp3
rsudp/rs_sounds/doorbell.mp3
rsudp/rs_sounds/sonar.mp3
rsudp/test/testdata.ms
rsudp-2.2.1.dist-info/licenses/LICENSE
rsudp-2.2.1.dist-info/METADATA
rsudp-2.2.1.dist-info/WHEEL
rsudp-2.2.1.dist-info/entry_points.txt
rsudp-2.2.1.dist-info/top_level.txt
rsudp-2.2.1.dist-info/RECORD
