Metadata-Version: 2.4
Name: rsudp
Version: 2.2.1
Summary: Tools for receiving and interacting with Raspberry Shake UDP data
Home-page: https://github.com/raspishake/rsudp
Author: Ian Nesbitt
Author-email: ian.nesbitt@raspberryshake.org
License: GPLv3
Classifier: License :: OSI Approved :: GNU General Public License v3 (GPLv3)
Classifier: Programming Language :: Python :: 3.10
Classifier: Programming Language :: Python :: 3.11
Classifier: Programming Language :: Python :: 3.12
Classifier: Operating System :: OS Independent
Classifier: Framework :: Matplotlib
Classifier: Topic :: Scientific/Engineering :: Physics
Classifier: Intended Audience :: Education
Classifier: Intended Audience :: End Users/Desktop
Classifier: Intended Audience :: Science/Research
Classifier: Intended Audience :: Developers
Classifier: Natural Language :: English
Classifier: Development Status :: 5 - Production/Stable
License-File: LICENSE
Requires-Dist: obspy
Requires-Dist: numpy<3,>=2.0.0
Requires-Dist: matplotlib<4,>3.2
Requires-Dist: pydub
Requires-Dist: twython
Requires-Dist: python-telegram-bot<21,>=20
Dynamic: author
Dynamic: author-email
Dynamic: classifier
Dynamic: description
Dynamic: description-content-type
Dynamic: home-page
Dynamic: license
Dynamic: license-file
Dynamic: requires-dist
Dynamic: summary
